<?xml version="1.0" encoding="utf-8"?>
<ode><userPreferences><userPreference><key>theme</key><value>base</value></userPreference></userPreferences><odeResources><odeResource><key>odeVersionId</key><value>20260425124005TNUOWZ</value></odeResource><odeResource><key>odeId</key><value>20260413102005QHLDIC</value></odeResource><odeResource><key>odeVersionName</key><value>0</value></odeResource><odeResource><key>isDownload</key><value>true</value></odeResource><odeResource><key>eXeVersion</key><value>v3.0.2</value></odeResource></odeResources><odeProperties><odeProperty><key>pp_title</key><value>Guardianes de la Biodiversidad</value></odeProperty><odeProperty><key>pp_subtitle</key><value>Explorando y protegiendo nuestros Ecosistemas</value></odeProperty><odeProperty><key>pp_lang</key><value>es</value></odeProperty><odeProperty><key>pp_author</key><value>Alba Isabel Núñez Guzmán</value></odeProperty><odeProperty><key>license</key><value>creative commons: attribution - share alike 4.0</value></odeProperty><odeProperty><key>pp_description</key><value>Situación de Aprendizaje diseñada para el alumnado de 5º de Educación Primaria, centrada en el estudio de los ecosistemas locales y la importancia de su preservación. A través de un enfoque basado en proyectos, el alumnado desarrollará habilidades de curación de contenidos digitales (búsqueda crítica y filtrado de información) y creación de contenidos multimedia. El objetivo final es que los alumnos elaboren un libro digital interactivo (Book Creator) y que recojan sus investigaciones, promoviendo el trabajo cooperativo, la competencia digital y la conciencia ecosocial.</value></odeProperty><odeProperty><key>exportSource</key><value>true</value></odeProperty><odeProperty><key>pp_addExeLink</key><value>true</value></odeProperty><odeProperty><key>pp_addPagination</key><value>false</value></odeProperty><odeProperty><key>pp_addSearchBox</key><value>false</value></odeProperty><odeProperty><key>pp_addAccessibilityToolbar</key><value>false</value></odeProperty><odeProperty><key>pp_extraHeadContent</key><value/></odeProperty><odeProperty><key>footer</key><value/></odeProperty></odeProperties><odeNavStructures><odeNavStructure><odePageId>20260425124005OIMMCS</odePageId><odeParentPageId/><pageName>SDA Guardianes de la Biodiversidad</pageName><odeNavStructureOrder>1</odeNavStructureOrder><odeNavStructureProperties><odeNavStructureProperty><key>titleNode</key><value>SDA Guardianes de la Biodiversidad</value></odeNavStructureProperty><odeNavStructureProperty><key>hidePageTitle</key><value>false</value></odeNavStructureProperty><odeNavStructureProperty><key>titleHtml</key><value/></odeNavStructureProperty><odeNavStructureProperty><key>editableInPage</key><value>false</value></odeNavStructureProperty><odeNavStructureProperty><key>titlePage</key><value>SDA Guardianes de la Biodiversidad</value></odeNavStructureProperty><odeNavStructureProperty><key>visibility</key><value>true</value></odeNavStructureProperty><odeNavStructureProperty><key>highlight</key><value>false</value></odeNavStructureProperty><odeNavStructureProperty><key>description</key><value/></odeNavStructureProperty></odeNavStructureProperties><odePagStructures><odePagStructure><odePageId>20260425124005OIMMCS</odePageId><odeBlockId>20260425124005HZUGZW</odeBlockId><blockName>Presentación</blockName><iconName>start</iconName><odePagStructureOrder>1</odePagStructureOrder><odePagStructureProperties><odePagStructureProperty><key>visibility</key><value>true</value></odePagStructureProperty><odePagStructureProperty><key>teacherOnly</key><value>false</value></odePagStructureProperty><odePagStructureProperty><key>allowToggle</key><value>true</value></odePagStructureProperty><odePagStructureProperty><key>minimized</key><value>false</value></odePagStructureProperty><odePagStructureProperty><key>identifier</key><value/></odePagStructureProperty><odePagStructureProperty><key>cssClass</key><value/></odePagStructureProperty></odePagStructureProperties><odeComponents><odeComponent><odePageId>20260425124005OIMMCS</odePageId><odeBlockId>20260425124005HZUGZW</odeBlockId><odeIdeviceId>20260413123220901WTK</odeIdeviceId><odeIdeviceTypeName>text</odeIdeviceTypeName><htmlView>&lt;div class="exe-text-template"&gt;&lt;div class="textIdeviceContent"&gt;
            &lt;div class="exe-text-activity"&gt;
                &lt;div&gt;&lt;p style="text-align: justify;"&gt;Bienvenidos al Proyecto: Guardianes de la Biodiversidad.&lt;/p&gt;
&lt;p style="text-align: justify;"&gt;En esta Situación de Aprendizaje, os convertiréis en investigadores ambientales. Vuestro reto es explorar los ecosistemas, comprender la importancia de su flora y fauna, y aprender a protegerlos.&lt;br&gt;&lt;/p&gt;
&lt;p style="text-align: justify;"&gt;&lt;strong&gt;¿Qué vamos a hacer? &lt;/strong&gt;Trabajaremos de forma colaborativa para buscar información real en internet (curación de contenidos) y, como producto final, crearemos un Libro Digital Interactivo en Book Creator para concienciar a los demás sobre la preservación de la naturaleza.&lt;/p&gt;
&lt;p style="text-align: justify;"&gt;&lt;strong&gt;Materias implicadas: &lt;/strong&gt;Conocimiento del Medio, Lengua Castellana y Educación Artística.&lt;br&gt;&lt;/p&gt;
&lt;p style="text-align: justify;"&gt;Este proyecto busca desarrollar vuestra competencia digital, enseñándoos a localizar y filtrar información de calidad en la red, siguiendo una metodología activa y participativa.&lt;/p&gt;
            &lt;div class="iDevice_buttons feedback-button js-required"&gt;
                &lt;input type="button" class="feedbacktooglebutton" value="Mostrar retroalimentación"&gt;
            &lt;/div&gt;
            &lt;div class="feedback js-feedback js-hidden"&gt;&lt;p style="text-align: justify;"&gt;¡Estamos muy emocionados de empezar este viaje con vosotros! Recordad que vuestra curiosidad es la mejor herramienta para salvar el planeta. ¡Ánimo, Guardianes!&lt;/p&gt;&lt;/div&gt;&lt;p class="clearfix"&gt;&lt;/p&gt;&lt;/div&gt;
            &lt;/div&gt;&lt;/div&gt;&lt;/div&gt;</htmlView><jsonProperties>{"ideviceId":"20260413123220901WTK","textInfoDurationInput":"","textInfoDurationTextInput":"Duración","textInfoParticipantsInput":"","textInfoParticipantsTextInput":"Agrupamiento","textTextarea":"&lt;p style=\"text-align: justify;\"&gt;Bienvenidos al Proyecto: Guardianes de la Biodiversidad.&lt;/p&gt;\n&lt;p style=\"text-align: justify;\"&gt;En esta Situación de Aprendizaje, os convertiréis en investigadores ambientales. Vuestro reto es explorar los ecosistemas, comprender la importancia de su flora y fauna, y aprender a protegerlos.&lt;br /&gt;&lt;/p&gt;\n&lt;p style=\"text-align: justify;\"&gt;&lt;strong&gt;¿Qué vamos a hacer? &lt;/strong&gt;Trabajaremos de forma colaborativa para buscar información real en internet (curación de contenidos) y, como producto final, crearemos un Libro Digital Interactivo en Book Creator para concienciar a los demás sobre la preservación de la naturaleza.&lt;/p&gt;\n&lt;p style=\"text-align: justify;\"&gt;&lt;strong&gt;Materias implicadas: &lt;/strong&gt;Conocimiento del Medio, Lengua Castellana y Educación Artística.&lt;br /&gt;&lt;/p&gt;\n&lt;p style=\"text-align: justify;\"&gt;Este proyecto busca desarrollar vuestra competencia digital, enseñándoos a localizar y filtrar información de calidad en la red, siguiendo una metodología activa y participativa.&lt;/p&gt;","textFeedbackInput":"Mostrar retroalimentación","textFeedbackTextarea":"&lt;p style=\"text-align: justify;\"&gt;¡Estamos muy emocionados de empezar este viaje con vosotros! Recordad que vuestra curiosidad es la mejor herramienta para salvar el planeta. ¡Ánimo, Guardianes!&lt;/p&gt;"}</jsonProperties><odeComponentsOrder>1</odeComponentsOrder><odeComponentsProperties><odeComponentsProperty><key>visibility</key><value>true</value></odeComponentsProperty><odeComponentsProperty><key>teacherOnly</key><value>false</value></odeComponentsProperty><odeComponentsProperty><key>identifier</key><value/></odeComponentsProperty><odeComponentsProperty><key>cssClass</key><value/></odeComponentsProperty></odeComponentsProperties></odeComponent></odeComponents></odePagStructure></odePagStructures></odeNavStructure><odeNavStructure><odePageId>20260425124005CBQZLB</odePageId><odeParentPageId>20260425124005OIMMCS</odeParentPageId><pageName>Protección de datos Personales y Derechos Digitales</pageName><odeNavStructureOrder>1</odeNavStructureOrder><odeNavStructureProperties><odeNavStructureProperty><key>titleNode</key><value/></odeNavStructureProperty><odeNavStructureProperty><key>hidePageTitle</key><value>false</value></odeNavStructureProperty><odeNavStructureProperty><key>titleHtml</key><value/></odeNavStructureProperty><odeNavStructureProperty><key>editableInPage</key><value>false</value></odeNavStructureProperty><odeNavStructureProperty><key>titlePage</key><value>Protección de datos Personales y Derechos Digitales</value></odeNavStructureProperty><odeNavStructureProperty><key>visibility</key><value>true</value></odeNavStructureProperty><odeNavStructureProperty><key>highlight</key><value>false</value></odeNavStructureProperty><odeNavStructureProperty><key>description</key><value/></odeNavStructureProperty></odeNavStructureProperties><odePagStructures><odePagStructure><odePageId>20260425124005CBQZLB</odePageId><odeBlockId>20260425124005XCWACC</odeBlockId><blockName>Navegando con seguridad y respeto</blockName><iconName>observe</iconName><odePagStructureOrder>1</odePagStructureOrder><odePagStructureProperties><odePagStructureProperty><key>visibility</key><value>true</value></odePagStructureProperty><odePagStructureProperty><key>teacherOnly</key><value>false</value></odePagStructureProperty><odePagStructureProperty><key>allowToggle</key><value>true</value></odePagStructureProperty><odePagStructureProperty><key>minimized</key><value>false</value></odePagStructureProperty><odePagStructureProperty><key>identifier</key><value/></odePagStructureProperty><odePagStructureProperty><key>cssClass</key><value/></odePagStructureProperty></odePagStructureProperties><odeComponents><odeComponent><odePageId>20260425124005CBQZLB</odePageId><odeBlockId>20260425124005XCWACC</odeBlockId><odeIdeviceId>20260413124247056CL7</odeIdeviceId><odeIdeviceTypeName>text</odeIdeviceTypeName><htmlView>&lt;div class="exe-text-template"&gt;&lt;div class="textIdeviceContent"&gt;
            &lt;div class="exe-text-activity"&gt;
                &lt;div&gt;&lt;p style="text-align: justify;"&gt;En este proyecto vamos a investigar y compartir muchas cosas en la red, pero recuerda: tus datos personales te pertenecen. No compartas nunca sin permiso de tus padres o profesores tu nombre completo, dirección, teléfono o fotos en las que se te reconozca claramente.&lt;/p&gt;
&lt;ul style="text-align: justify;"&gt;
&lt;li&gt;Contraseñas secretas: Son como llaves, no se las des a nadie.&lt;/li&gt;
&lt;li&gt;Pide permiso: Antes de registrarte en cualquier aplicación que usemos para el libro digital, asegúrate de que es apta para tu edad.&lt;/li&gt;
&lt;li&gt;Huella digital: Todo lo que hacemos en internet deja rastro. ¡Haz que el tuyo sea positivo y respetuoso!&lt;/li&gt;
&lt;/ul&gt;
&lt;p style="text-align: justify;"&gt;Al igual que en el mundo real, en el mundo digital tienes derechos. Tienes derecho a ser respetado y a que se cuide tu privacidad. Pero también tienes el deber de respetar el trabajo de los demás:&lt;/p&gt;
&lt;ul&gt;
&lt;li style="text-align: justify;"&gt;Cuando uses una imagen o un vídeo para tu libro digital, debemos citar quién es su autor.&lt;/li&gt;
&lt;li style="text-align: justify;"&gt;Trata a tus compañeros en la red como te gustaría que te trataran a ti.&lt;/li&gt;
&lt;/ul&gt;&lt;p class="clearfix"&gt;&lt;/p&gt;&lt;/div&gt;
            &lt;/div&gt;&lt;/div&gt;&lt;/div&gt;</htmlView><jsonProperties>{"ideviceId":"20260413124247056CL7","textInfoDurationInput":"","textInfoDurationTextInput":"Duración","textInfoParticipantsInput":"","textInfoParticipantsTextInput":"Agrupamiento","textTextarea":"&lt;p style=\"text-align: justify;\"&gt;En este proyecto vamos a investigar y compartir muchas cosas en la red, pero recuerda: tus datos personales te pertenecen. No compartas nunca sin permiso de tus padres o profesores tu nombre completo, dirección, teléfono o fotos en las que se te reconozca claramente.&lt;/p&gt;\n&lt;ul style=\"text-align: justify;\"&gt;\n&lt;li&gt;Contraseñas secretas: Son como llaves, no se las des a nadie.&lt;/li&gt;\n&lt;li&gt;Pide permiso: Antes de registrarte en cualquier aplicación que usemos para el libro digital, asegúrate de que es apta para tu edad.&lt;/li&gt;\n&lt;li&gt;Huella digital: Todo lo que hacemos en internet deja rastro. ¡Haz que el tuyo sea positivo y respetuoso!&lt;/li&gt;\n&lt;/ul&gt;\n&lt;p style=\"text-align: justify;\"&gt;Al igual que en el mundo real, en el mundo digital tienes derechos. Tienes derecho a ser respetado y a que se cuide tu privacidad. Pero también tienes el deber de respetar el trabajo de los demás:&lt;/p&gt;\n&lt;ul&gt;\n&lt;li style=\"text-align: justify;\"&gt;Cuando uses una imagen o un vídeo para tu libro digital, debemos citar quién es su autor.&lt;/li&gt;\n&lt;li style=\"text-align: justify;\"&gt;Trata a tus compañeros en la red como te gustaría que te trataran a ti.&lt;/li&gt;\n&lt;/ul&gt;","textFeedbackInput":"Mostrar retroalimentación","textFeedbackTextarea":""}</jsonProperties><odeComponentsOrder>1</odeComponentsOrder><odeComponentsProperties><odeComponentsProperty><key>visibility</key><value>true</value></odeComponentsProperty><odeComponentsProperty><key>teacherOnly</key><value>false</value></odeComponentsProperty><odeComponentsProperty><key>identifier</key><value/></odeComponentsProperty><odeComponentsProperty><key>cssClass</key><value/></odeComponentsProperty></odeComponentsProperties></odeComponent></odeComponents></odePagStructure></odePagStructures></odeNavStructure><odeNavStructure><odePageId>20260425124005OYBXTK</odePageId><odeParentPageId>20260425124005CBQZLB</odeParentPageId><pageName>Nuestro reto: Libro Digital</pageName><odeNavStructureOrder>1</odeNavStructureOrder><odeNavStructureProperties><odeNavStructureProperty><key>titleNode</key><value/></odeNavStructureProperty><odeNavStructureProperty><key>hidePageTitle</key><value>false</value></odeNavStructureProperty><odeNavStructureProperty><key>titleHtml</key><value/></odeNavStructureProperty><odeNavStructureProperty><key>editableInPage</key><value>false</value></odeNavStructureProperty><odeNavStructureProperty><key>titlePage</key><value>Nuestro reto: Libro Digital</value></odeNavStructureProperty><odeNavStructureProperty><key>visibility</key><value>true</value></odeNavStructureProperty><odeNavStructureProperty><key>highlight</key><value>false</value></odeNavStructureProperty><odeNavStructureProperty><key>description</key><value/></odeNavStructureProperty></odeNavStructureProperties><odePagStructures><odePagStructure><odePageId>20260425124005OYBXTK</odePageId><odeBlockId>20260425124005MRGQBS</odeBlockId><blockName>Libro Digital</blockName><iconName>technology</iconName><odePagStructureOrder>1</odePagStructureOrder><odePagStructureProperties><odePagStructureProperty><key>visibility</key><value>true</value></odePagStructureProperty><odePagStructureProperty><key>teacherOnly</key><value>false</value></odePagStructureProperty><odePagStructureProperty><key>allowToggle</key><value>true</value></odePagStructureProperty><odePagStructureProperty><key>minimized</key><value>false</value></odePagStructureProperty><odePagStructureProperty><key>identifier</key><value/></odePagStructureProperty><odePagStructureProperty><key>cssClass</key><value/></odePagStructureProperty></odePagStructureProperties><odeComponents><odeComponent><odePageId>20260425124005OYBXTK</odePageId><odeBlockId>20260425124005MRGQBS</odeBlockId><odeIdeviceId>20260415161557628CF4</odeIdeviceId><odeIdeviceTypeName>text</odeIdeviceTypeName><htmlView>&lt;div class="exe-text-template"&gt;&lt;div class="textIdeviceContent"&gt;
            &lt;div class="exe-text-activity"&gt;
                &lt;div&gt;&lt;p style="text-align: justify;"&gt;¡Ha llegado el momento de convertirnos en autores!&lt;/p&gt;
&lt;p style="text-align: justify;"&gt;Vuestro desafío principal en este proyecto consiste en crear, por equipos, un Libro Digital Interactivo sobre el ecosistema que hayáis investigado. Para ello utilizaremos la herramienta Book Creator. Vuestro libro no solo debe tener texto; para que sea un verdadero recurso del siglo XXI, deberá incluir:&lt;/p&gt;
&lt;ul&gt;
&lt;li&gt;Imágenes impactantes del ecosistema.&lt;/li&gt;
&lt;li&gt;Audios con vuestras explicaciones sobre la fauna y flora.&lt;/li&gt;
&lt;li&gt;Vídeos o enlaces a curiosidades que hayáis encontrado.&lt;/li&gt;
&lt;/ul&gt;
&lt;p&gt;El objetivo es que cualquier persona que lea vuestro libro aprenda por qué es vital proteger nuestra biodiversidad.&lt;/p&gt;&lt;p class="clearfix"&gt;&lt;/p&gt;&lt;/div&gt;
            &lt;/div&gt;&lt;/div&gt;&lt;/div&gt;</htmlView><jsonProperties>{"ideviceId":"20260415161557628CF4","textInfoDurationInput":"","textInfoDurationTextInput":"Duración","textInfoParticipantsInput":"","textInfoParticipantsTextInput":"Agrupamiento","textTextarea":"&lt;p style=\"text-align: justify;\"&gt;¡Ha llegado el momento de convertirnos en autores!&lt;/p&gt;\n&lt;p style=\"text-align: justify;\"&gt;Vuestro desafío principal en este proyecto consiste en crear, por equipos, un Libro Digital Interactivo sobre el ecosistema que hayáis investigado. Para ello utilizaremos la herramienta Book Creator. Vuestro libro no solo debe tener texto; para que sea un verdadero recurso del siglo XXI, deberá incluir:&lt;/p&gt;\n&lt;ul&gt;\n&lt;li&gt;Imágenes impactantes del ecosistema.&lt;/li&gt;\n&lt;li&gt;Audios con vuestras explicaciones sobre la fauna y flora.&lt;/li&gt;\n&lt;li&gt;Vídeos o enlaces a curiosidades que hayáis encontrado.&lt;/li&gt;\n&lt;/ul&gt;\n&lt;p&gt;El objetivo es que cualquier persona que lea vuestro libro aprenda por qué es vital proteger nuestra biodiversidad.&lt;/p&gt;","textFeedbackInput":"Mostrar retroalimentación","textFeedbackTextarea":""}</jsonProperties><odeComponentsOrder>1</odeComponentsOrder><odeComponentsProperties><odeComponentsProperty><key>visibility</key><value>true</value></odeComponentsProperty><odeComponentsProperty><key>teacherOnly</key><value>false</value></odeComponentsProperty><odeComponentsProperty><key>identifier</key><value/></odeComponentsProperty><odeComponentsProperty><key>cssClass</key><value/></odeComponentsProperty></odeComponentsProperties></odeComponent></odeComponents></odePagStructure></odePagStructures></odeNavStructure><odeNavStructure><odePageId>20260425124005AMHYYT</odePageId><odeParentPageId>20260425124005OYBXTK</odeParentPageId><pageName>Caja de herramientas</pageName><odeNavStructureOrder>1</odeNavStructureOrder><odeNavStructureProperties><odeNavStructureProperty><key>titleNode</key><value/></odeNavStructureProperty><odeNavStructureProperty><key>hidePageTitle</key><value>false</value></odeNavStructureProperty><odeNavStructureProperty><key>titleHtml</key><value/></odeNavStructureProperty><odeNavStructureProperty><key>editableInPage</key><value>false</value></odeNavStructureProperty><odeNavStructureProperty><key>titlePage</key><value>Caja de herramientas</value></odeNavStructureProperty><odeNavStructureProperty><key>visibility</key><value>true</value></odeNavStructureProperty><odeNavStructureProperty><key>highlight</key><value>false</value></odeNavStructureProperty><odeNavStructureProperty><key>description</key><value/></odeNavStructureProperty></odeNavStructureProperties><odePagStructures><odePagStructure><odePageId>20260425124005AMHYYT</odePageId><odeBlockId>20260425124005PNQADC</odeBlockId><blockName>Herramientas</blockName><iconName>download</iconName><odePagStructureOrder>1</odePagStructureOrder><odePagStructureProperties><odePagStructureProperty><key>visibility</key><value>true</value></odePagStructureProperty><odePagStructureProperty><key>teacherOnly</key><value>false</value></odePagStructureProperty><odePagStructureProperty><key>allowToggle</key><value>true</value></odePagStructureProperty><odePagStructureProperty><key>minimized</key><value>false</value></odePagStructureProperty><odePagStructureProperty><key>identifier</key><value/></odePagStructureProperty><odePagStructureProperty><key>cssClass</key><value/></odePagStructureProperty></odePagStructureProperties><odeComponents><odeComponent><odePageId>20260425124005AMHYYT</odePageId><odeBlockId>20260425124005PNQADC</odeBlockId><odeIdeviceId>2026041516244013292U</odeIdeviceId><odeIdeviceTypeName>text</odeIdeviceTypeName><htmlView>&lt;div class="exe-text-template"&gt;&lt;div class="textIdeviceContent"&gt;
            &lt;div class="exe-text-activity"&gt;
                &lt;div&gt;&lt;p&gt;En esta sección encontrarás las herramientas necesarias tanto para vuestras investigaciones como para la gestión del trabajo diario en clase.&amp;nbsp;&lt;/p&gt;
&lt;p&gt;1. Recursos para alumnado (Symbaloo)&lt;br&gt;&lt;/p&gt;
&lt;p&gt;Este panel ha sido diseñado específicamente para ayudaros en la creación de vuestro Libro Digital Interactivo. No son solo juegos, son recursos para aprender e investigar de forma profesional.&lt;/p&gt;
&lt;p&gt;&lt;a href="https://www.symbaloo.com/home/mix/13eP7EPKWN"&gt;https://www.symbaloo.com/home/mix/13eP7EPKWN&lt;/a&gt;&lt;/p&gt;
&lt;p&gt;2. Recursos gestión docente (Padlet)&lt;br&gt;&lt;/p&gt;
&lt;p&gt;Este espacio está dirigido a otros profesores que quieran conocer las herramientas que utilizamos en nuestro día a día para que el aula funcione perfectamente y podamos aprender mejor.&amp;nbsp;&lt;/p&gt;
&lt;p&gt;&lt;a href="https://padlet.com/albanunez7/recursos-aula-vk326xojsvpxl4a0"&gt;https://padlet.com/albanunez7/recursos-aula-vk326xojsvpxl4a0&lt;/a&gt;&lt;/p&gt;
&lt;p&gt;&lt;br&gt;&amp;nbsp;&lt;br&gt;&lt;br&gt;&lt;br&gt;&lt;/p&gt;&lt;p class="clearfix"&gt;&lt;/p&gt;&lt;/div&gt;
            &lt;/div&gt;&lt;/div&gt;&lt;/div&gt;</htmlView><jsonProperties>{"ideviceId":"2026041516244013292U","textInfoDurationInput":"","textInfoDurationTextInput":"Duración","textInfoParticipantsInput":"","textInfoParticipantsTextInput":"Agrupamiento","textTextarea":"&lt;p&gt;En esta sección encontrarás las herramientas necesarias tanto para vuestras investigaciones como para la gestión del trabajo diario en clase. &lt;/p&gt;\n&lt;p&gt;1. Recursos para alumnado (Symbaloo)&lt;br /&gt;&lt;/p&gt;\n&lt;p&gt;Este panel ha sido diseñado específicamente para ayudaros en la creación de vuestro Libro Digital Interactivo. No son solo juegos, son recursos para aprender e investigar de forma profesional.&lt;/p&gt;\n&lt;p&gt;&lt;a href=\"https://www.symbaloo.com/home/mix/13eP7EPKWN\"&gt;https://www.symbaloo.com/home/mix/13eP7EPKWN&lt;/a&gt;&lt;/p&gt;\n&lt;p&gt;2. Recursos gestión docente (Padlet)&lt;br /&gt;&lt;/p&gt;\n&lt;p&gt;Este espacio está dirigido a otros profesores que quieran conocer las herramientas que utilizamos en nuestro día a día para que el aula funcione perfectamente y podamos aprender mejor. &lt;/p&gt;\n&lt;p&gt;&lt;a href=\"https://padlet.com/albanunez7/recursos-aula-vk326xojsvpxl4a0\"&gt;https://padlet.com/albanunez7/recursos-aula-vk326xojsvpxl4a0&lt;/a&gt;&lt;/p&gt;\n&lt;p&gt;&lt;br /&gt; &lt;br /&gt;&lt;br /&gt;&lt;br /&gt;&lt;/p&gt;","textFeedbackInput":"Mostrar retroalimentación","textFeedbackTextarea":""}</jsonProperties><odeComponentsOrder>1</odeComponentsOrder><odeComponentsProperties><odeComponentsProperty><key>visibility</key><value>true</value></odeComponentsProperty><odeComponentsProperty><key>teacherOnly</key><value>false</value></odeComponentsProperty><odeComponentsProperty><key>identifier</key><value/></odeComponentsProperty><odeComponentsProperty><key>cssClass</key><value/></odeComponentsProperty></odeComponentsProperties></odeComponent></odeComponents></odePagStructure></odePagStructures></odeNavStructure><odeNavStructure><odePageId>20260425124005VVUDTE</odePageId><odeParentPageId>20260425124005AMHYYT</odeParentPageId><pageName>Nuestra hoja de ruta</pageName><odeNavStructureOrder>1</odeNavStructureOrder><odeNavStructureProperties><odeNavStructureProperty><key>titleNode</key><value>Nuestra hoja de ruta</value></odeNavStructureProperty><odeNavStructureProperty><key>hidePageTitle</key><value>false</value></odeNavStructureProperty><odeNavStructureProperty><key>titleHtml</key><value/></odeNavStructureProperty><odeNavStructureProperty><key>editableInPage</key><value>false</value></odeNavStructureProperty><odeNavStructureProperty><key>titlePage</key><value>Nuestra hoja de ruta</value></odeNavStructureProperty><odeNavStructureProperty><key>visibility</key><value>true</value></odeNavStructureProperty><odeNavStructureProperty><key>highlight</key><value>false</value></odeNavStructureProperty><odeNavStructureProperty><key>description</key><value/></odeNavStructureProperty></odeNavStructureProperties><odePagStructures><odePagStructure><odePageId>20260425124005VVUDTE</odePageId><odeBlockId>20260425124005QXXHXD</odeBlockId><blockName>Ruta</blockName><iconName>stop</iconName><odePagStructureOrder>1</odePagStructureOrder><odePagStructureProperties><odePagStructureProperty><key>visibility</key><value>true</value></odePagStructureProperty><odePagStructureProperty><key>teacherOnly</key><value>false</value></odePagStructureProperty><odePagStructureProperty><key>allowToggle</key><value>true</value></odePagStructureProperty><odePagStructureProperty><key>minimized</key><value>false</value></odePagStructureProperty><odePagStructureProperty><key>identifier</key><value/></odePagStructureProperty><odePagStructureProperty><key>cssClass</key><value/></odePagStructureProperty></odePagStructureProperties><odeComponents><odeComponent><odePageId>20260425124005VVUDTE</odePageId><odeBlockId>20260425124005QXXHXD</odeBlockId><odeIdeviceId>20260415163451417WKK</odeIdeviceId><odeIdeviceTypeName>text</odeIdeviceTypeName><htmlView>&lt;div class="exe-text-template"&gt;&lt;div class="textIdeviceContent"&gt;
            &lt;div class="exe-text-activity"&gt;
                &lt;div&gt;&lt;p style="text-align: justify;"&gt;Para que no os perdáis en nuestra aventura como Guardianes de la Biodiversidad, aquí tenéis nuestra planificación detallada. En este mapa podréis ver qué haremos cada día, con quién trabajaréis y qué herramientas digitales necesitaremos para salvar nuestros ecosistemas.&lt;/p&gt;
&lt;p style="text-align: justify;"&gt;&lt;img src="{{context_path}}/20260415163451417WKK/Captura_de_pantalla_2026-04-15_a_las_17.19.03.png" width="1440" height="783" alt=""&gt;&lt;/p&gt;
&lt;p style="text-align: justify;"&gt;&lt;img src="{{context_path}}/20260415163451417WKK/Modulo_7.pdf" alt=""&gt;&lt;/p&gt;&lt;p class="clearfix"&gt;&lt;/p&gt;&lt;/div&gt;
            &lt;/div&gt;&lt;/div&gt;&lt;/div&gt;</htmlView><jsonProperties>{"ideviceId":"20260415163451417WKK","textInfoDurationInput":"","textInfoDurationTextInput":"Duración","textInfoParticipantsInput":"","textInfoParticipantsTextInput":"Agrupamiento","textTextarea":"&lt;p style=\"text-align: justify;\"&gt;Para que no os perdáis en nuestra aventura como Guardianes de la Biodiversidad, aquí tenéis nuestra planificación detallada. En este mapa podréis ver qué haremos cada día, con quién trabajaréis y qué herramientas digitales necesitaremos para salvar nuestros ecosistemas.&lt;/p&gt;\n&lt;p style=\"text-align: justify;\"&gt;&lt;img src=\"{{context_path}}/20260415163451417WKK/Captura_de_pantalla_2026-04-15_a_las_17.19.03.png\" width=\"1440\" height=\"783\" alt=\"\" /&gt;&lt;/p&gt;\n&lt;p style=\"text-align: justify;\"&gt;&lt;img src=\"{{context_path}}/20260415163451417WKK/Modulo_7.pdf\" alt=\"\" /&gt;&lt;/p&gt;","textFeedbackInput":"Mostrar retroalimentación","textFeedbackTextarea":""}</jsonProperties><odeComponentsOrder>1</odeComponentsOrder><odeComponentsProperties><odeComponentsProperty><key>visibility</key><value>true</value></odeComponentsProperty><odeComponentsProperty><key>teacherOnly</key><value>false</value></odeComponentsProperty><odeComponentsProperty><key>identifier</key><value/></odeComponentsProperty><odeComponentsProperty><key>cssClass</key><value/></odeComponentsProperty></odeComponentsProperties></odeComponent></odeComponents></odePagStructure></odePagStructures></odeNavStructure><odeNavStructure><odePageId>20260425124005UUMDSX</odePageId><odeParentPageId>20260425124005VVUDTE</odeParentPageId><pageName>Guía didáctica</pageName><odeNavStructureOrder>1</odeNavStructureOrder><odeNavStructureProperties><odeNavStructureProperty><key>titleNode</key><value/></odeNavStructureProperty><odeNavStructureProperty><key>hidePageTitle</key><value>false</value></odeNavStructureProperty><odeNavStructureProperty><key>titleHtml</key><value/></odeNavStructureProperty><odeNavStructureProperty><key>editableInPage</key><value>false</value></odeNavStructureProperty><odeNavStructureProperty><key>titlePage</key><value>Guía didáctica</value></odeNavStructureProperty><odeNavStructureProperty><key>visibility</key><value>true</value></odeNavStructureProperty><odeNavStructureProperty><key>highlight</key><value>false</value></odeNavStructureProperty><odeNavStructureProperty><key>description</key><value/></odeNavStructureProperty></odeNavStructureProperties><odePagStructures><odePagStructure><odePageId>20260425124005UUMDSX</odePageId><odeBlockId>20260425124005HVHZEM</odeBlockId><blockName>Guía</blockName><iconName>activity</iconName><odePagStructureOrder>1</odePagStructureOrder><odePagStructureProperties><odePagStructureProperty><key>visibility</key><value>true</value></odePagStructureProperty><odePagStructureProperty><key>teacherOnly</key><value>false</value></odePagStructureProperty><odePagStructureProperty><key>allowToggle</key><value>true</value></odePagStructureProperty><odePagStructureProperty><key>minimized</key><value>false</value></odePagStructureProperty><odePagStructureProperty><key>identifier</key><value/></odePagStructureProperty><odePagStructureProperty><key>cssClass</key><value/></odePagStructureProperty></odePagStructureProperties><odeComponents><odeComponent><odePageId>20260425124005UUMDSX</odePageId><odeBlockId>20260425124005HVHZEM</odeBlockId><odeIdeviceId>202604151650536311OO</odeIdeviceId><odeIdeviceTypeName>text</odeIdeviceTypeName><htmlView>&lt;div class="exe-text-template"&gt;&lt;div class="textIdeviceContent"&gt;
            &lt;div class="exe-text-activity"&gt;
                &lt;div&gt;&lt;p style="text-align: justify;"&gt;&lt;strong&gt;¿Cómo vamos a saber qué hemos aprendido?&lt;/strong&gt;&lt;/p&gt;
&lt;p style="text-align: justify;"&gt;Evaluar no es solo poner una nota final, es una forma de darnos cuenta de lo que estamos haciendo genial y de lo que podemos mejorar juntos mientras salvamos nuestros ecosistemas. Para este proyecto, utilizaremos diferentes herramientas que nos ayudarán a ver vuestro progreso.&lt;/p&gt;
&lt;p style="text-align: justify;"&gt;&lt;strong&gt;1. Nuestra Tabla de Logros&lt;/strong&gt;&lt;br&gt;&lt;/p&gt;
&lt;p style="text-align: justify;"&gt;Aquí podéis ver qué tareas vamos a realizar y qué es lo que tendremos en cuenta:&lt;/p&gt;
&lt;ul&gt;
&lt;li style="text-align: justify;"&gt;Tarea:&lt;br&gt;&lt;/li&gt;
&lt;/ul&gt;
&lt;p&gt;- Investigación inicial.&amp;nbsp;&lt;/p&gt;
&lt;p&gt;- Esquema digital.&amp;nbsp;&lt;/p&gt;
&lt;p&gt;- Libro Digital.&amp;nbsp;&lt;/p&gt;
&lt;ul&gt;
&lt;li&gt;¿Qué evaluamos? (criterios)&amp;nbsp;&lt;/li&gt;
&lt;/ul&gt;
&lt;p style="text-align: justify;"&gt;- Búsqueda crítica de información sobre ecosistemas.&amp;nbsp;&lt;/p&gt;
&lt;p style="text-align: justify;"&gt;- Organización clara de ideas principales.&amp;nbsp;&lt;/p&gt;
&lt;p style="text-align: justify;"&gt;- Creación de contenidos multimedia y respeto a la autoría.&lt;/p&gt;
&lt;p style="text-align: justify;"&gt;- Explicación clara y uso de vocabulario científico.&lt;/p&gt;
&lt;ul&gt;
&lt;li style="text-align: justify;"&gt;¿Cómo lo haremos?&amp;nbsp;&lt;/li&gt;
&lt;/ul&gt;
&lt;p&gt;- Observación en clase y diario.&lt;/p&gt;
&lt;p&gt;- Revisión del esquema.&amp;nbsp;&lt;/p&gt;
&lt;p&gt;- Rúbrica del Libro Digital.&amp;nbsp;&lt;/p&gt;
&lt;p&gt;- Diana de autoevaluación.&amp;nbsp;&lt;br&gt;&lt;strong&gt;2. La Rúbrica de nuestro Libro Digital&lt;/strong&gt;&lt;/p&gt;
&lt;p style="text-align: justify;"&gt;Para que vuestro libro digital sea excelente, usaremos una rúbrica. Es como una guía que os dice qué pasos seguir para ser unos "Súper Guardianes". Tendremos en cuenta:&lt;/p&gt;
&lt;p style="text-align: justify;"&gt;- Si la información es clara y real.&lt;br&gt;- Si habéis incluido imágenes y audios propios.&lt;br&gt;- Si habéis trabajado bien en equipo.&lt;br&gt;- Si habéis citado de dónde habéis sacado la información.&lt;br&gt;&lt;/p&gt;
&lt;p style="text-align: justify;"&gt;&lt;strong&gt;3. Nuestra Diana de Autoevaluación&lt;/strong&gt;&lt;br&gt;&lt;/p&gt;
&lt;p style="text-align: justify;"&gt;Al final de cada misión, vosotros mismos podréis ver vuestro esfuerzo con la Diana de Autoevaluación. Dibujaremos puntos en los ejes de:&lt;/p&gt;
&lt;p style="text-align: justify;"&gt;- Responsabilidad: ¿He cumplido con mi parte del trabajo?&lt;br&gt;- Ayuda: ¿He ayudado a mis compañeros cuando lo necesitaban?&lt;br&gt;- Respeto: ¿He escuchado las ideas de los demás?&lt;br&gt;- Plazos: ¿He terminado las tareas a tiempo?&lt;br&gt;&lt;/p&gt;
&lt;p style="text-align: justify;"&gt;&lt;strong&gt;¿Para qué sirven estos datos?&lt;/strong&gt;&lt;br&gt;&lt;/p&gt;
&lt;p style="text-align: justify;"&gt;Toda la información que recojamos con estas herramientas nos servirá para daros consejos y pistas (feedback) que os ayuden a mejorar antes de la entrega final. ¡Recordad que el objetivo es aprender y disfrutar protegiendo la naturaleza!&amp;nbsp;&lt;/p&gt;
&lt;p&gt;&lt;img src="{{context_path}}/202604151650536311OO/Captura_de_pantalla_2026-04-15_a_las_17.08.54_1.png" width="236" height="180" alt=""&gt; &lt;img src="{{context_path}}/202604151650536311OO/Captura_de_pantalla_2026-04-15_a_las_17.08.44_1.png" width="399" height="287" alt=""&gt;&lt;br&gt;&lt;br&gt;&lt;/p&gt;&lt;p class="clearfix"&gt;&lt;/p&gt;&lt;/div&gt;
            &lt;/div&gt;&lt;/div&gt;&lt;/div&gt;</htmlView><jsonProperties>{"ideviceId":"202604151650536311OO","textInfoDurationInput":"","textInfoDurationTextInput":"Duración","textInfoParticipantsInput":"","textInfoParticipantsTextInput":"Agrupamiento","textTextarea":"&lt;p style=\"text-align: justify;\"&gt;&lt;strong&gt;¿Cómo vamos a saber qué hemos aprendido?&lt;/strong&gt;&lt;/p&gt;\n&lt;p style=\"text-align: justify;\"&gt;Evaluar no es solo poner una nota final, es una forma de darnos cuenta de lo que estamos haciendo genial y de lo que podemos mejorar juntos mientras salvamos nuestros ecosistemas. Para este proyecto, utilizaremos diferentes herramientas que nos ayudarán a ver vuestro progreso.&lt;/p&gt;\n&lt;p style=\"text-align: justify;\"&gt;&lt;strong&gt;1. Nuestra Tabla de Logros&lt;/strong&gt;&lt;br /&gt;&lt;/p&gt;\n&lt;p style=\"text-align: justify;\"&gt;Aquí podéis ver qué tareas vamos a realizar y qué es lo que tendremos en cuenta:&lt;/p&gt;\n&lt;ul&gt;\n&lt;li style=\"text-align: justify;\"&gt;Tarea:&lt;br /&gt;&lt;/li&gt;\n&lt;/ul&gt;\n&lt;p&gt;- Investigación inicial. &lt;/p&gt;\n&lt;p&gt;- Esquema digital. &lt;/p&gt;\n&lt;p&gt;- Libro Digital. &lt;/p&gt;\n&lt;ul&gt;\n&lt;li&gt;¿Qué evaluamos? (criterios) &lt;/li&gt;\n&lt;/ul&gt;\n&lt;p style=\"text-align: justify;\"&gt;- Búsqueda crítica de información sobre ecosistemas. &lt;/p&gt;\n&lt;p style=\"text-align: justify;\"&gt;- Organización clara de ideas principales. &lt;/p&gt;\n&lt;p style=\"text-align: justify;\"&gt;- Creación de contenidos multimedia y respeto a la autoría.&lt;/p&gt;\n&lt;p style=\"text-align: justify;\"&gt;- Explicación clara y uso de vocabulario científico.&lt;/p&gt;\n&lt;ul&gt;\n&lt;li style=\"text-align: justify;\"&gt;¿Cómo lo haremos? &lt;/li&gt;\n&lt;/ul&gt;\n&lt;p&gt;- Observación en clase y diario.&lt;/p&gt;\n&lt;p&gt;- Revisión del esquema. &lt;/p&gt;\n&lt;p&gt;- Rúbrica del Libro Digital. &lt;/p&gt;\n&lt;p&gt;- Diana de autoevaluación. &lt;br /&gt;&lt;strong&gt;2. La Rúbrica de nuestro Libro Digital&lt;/strong&gt;&lt;/p&gt;\n&lt;p style=\"text-align: justify;\"&gt;Para que vuestro libro digital sea excelente, usaremos una rúbrica. Es como una guía que os dice qué pasos seguir para ser unos \"Súper Guardianes\". Tendremos en cuenta:&lt;/p&gt;\n&lt;p style=\"text-align: justify;\"&gt;- Si la información es clara y real.&lt;br /&gt;- Si habéis incluido imágenes y audios propios.&lt;br /&gt;- Si habéis trabajado bien en equipo.&lt;br /&gt;- Si habéis citado de dónde habéis sacado la información.&lt;br /&gt;&lt;/p&gt;\n&lt;p style=\"text-align: justify;\"&gt;&lt;strong&gt;3. Nuestra Diana de Autoevaluación&lt;/strong&gt;&lt;br /&gt;&lt;/p&gt;\n&lt;p style=\"text-align: justify;\"&gt;Al final de cada misión, vosotros mismos podréis ver vuestro esfuerzo con la Diana de Autoevaluación. Dibujaremos puntos en los ejes de:&lt;/p&gt;\n&lt;p style=\"text-align: justify;\"&gt;- Responsabilidad: ¿He cumplido con mi parte del trabajo?&lt;br /&gt;- Ayuda: ¿He ayudado a mis compañeros cuando lo necesitaban?&lt;br /&gt;- Respeto: ¿He escuchado las ideas de los demás?&lt;br /&gt;- Plazos: ¿He terminado las tareas a tiempo?&lt;br /&gt;&lt;/p&gt;\n&lt;p style=\"text-align: justify;\"&gt;&lt;strong&gt;¿Para qué sirven estos datos?&lt;/strong&gt;&lt;br /&gt;&lt;/p&gt;\n&lt;p style=\"text-align: justify;\"&gt;Toda la información que recojamos con estas herramientas nos servirá para daros consejos y pistas (feedback) que os ayuden a mejorar antes de la entrega final. ¡Recordad que el objetivo es aprender y disfrutar protegiendo la naturaleza! &lt;/p&gt;\n&lt;p&gt;&lt;img src=\"{{context_path}}/202604151650536311OO/Captura_de_pantalla_2026-04-15_a_las_17.08.54_1.png\" width=\"236\" height=\"180\" alt=\"\" /&gt; &lt;img src=\"{{context_path}}/202604151650536311OO/Captura_de_pantalla_2026-04-15_a_las_17.08.44_1.png\" width=\"399\" height=\"287\" alt=\"\" /&gt;&lt;br /&gt;&lt;br /&gt;&lt;/p&gt;","textFeedbackInput":"Mostrar retroalimentación","textFeedbackTextarea":""}</jsonProperties><odeComponentsOrder>1</odeComponentsOrder><odeComponentsProperties><odeComponentsProperty><key>visibility</key><value>true</value></odeComponentsProperty><odeComponentsProperty><key>teacherOnly</key><value>false</value></odeComponentsProperty><odeComponentsProperty><key>identifier</key><value/></odeComponentsProperty><odeComponentsProperty><key>cssClass</key><value/></odeComponentsProperty></odeComponentsProperties></odeComponent></odeComponents></odePagStructure></odePagStructures></odeNavStructure><odeNavStructure><odePageId>20260425124005XPMVZC</odePageId><odeParentPageId>20260425124005UUMDSX</odeParentPageId><pageName>Créditos</pageName><odeNavStructureOrder>1</odeNavStructureOrder><odeNavStructureProperties><odeNavStructureProperty><key>titleNode</key><value/></odeNavStructureProperty><odeNavStructureProperty><key>hidePageTitle</key><value>false</value></odeNavStructureProperty><odeNavStructureProperty><key>titleHtml</key><value/></odeNavStructureProperty><odeNavStructureProperty><key>editableInPage</key><value>false</value></odeNavStructureProperty><odeNavStructureProperty><key>titlePage</key><value>Créditos</value></odeNavStructureProperty><odeNavStructureProperty><key>visibility</key><value>true</value></odeNavStructureProperty><odeNavStructureProperty><key>highlight</key><value>false</value></odeNavStructureProperty><odeNavStructureProperty><key>description</key><value/></odeNavStructureProperty></odeNavStructureProperties><odePagStructures><odePagStructure><odePageId>20260425124005XPMVZC</odePageId><odeBlockId>20260425124005ZDESZG</odeBlockId><blockName>Créditos</blockName><iconName>agreement</iconName><odePagStructureOrder>1</odePagStructureOrder><odePagStructureProperties><odePagStructureProperty><key>visibility</key><value>true</value></odePagStructureProperty><odePagStructureProperty><key>teacherOnly</key><value>false</value></odePagStructureProperty><odePagStructureProperty><key>allowToggle</key><value>true</value></odePagStructureProperty><odePagStructureProperty><key>minimized</key><value>false</value></odePagStructureProperty><odePagStructureProperty><key>identifier</key><value/></odePagStructureProperty><odePagStructureProperty><key>cssClass</key><value/></odePagStructureProperty></odePagStructureProperties><odeComponents><odeComponent><odePageId>20260425124005XPMVZC</odePageId><odeBlockId>20260425124005ZDESZG</odeBlockId><odeIdeviceId>20260415194001424SCS</odeIdeviceId><odeIdeviceTypeName>text</odeIdeviceTypeName><htmlView>&lt;div class="exe-text-template"&gt;&lt;div class="textIdeviceContent"&gt;
            &lt;div class="exe-text-activity"&gt;
                &lt;div&gt;&lt;p&gt;&lt;strong&gt;Autoría: &lt;/strong&gt;Alba Isabel Núñez Guzmán.&amp;nbsp;&lt;/p&gt;
&lt;p&gt;&lt;strong&gt;Descripción del recurso:&lt;/strong&gt; Situación de Aprendizaje (SdA) titulada "Guardianes de la Biodiversidad", diseñada para alumnos de 5.º de Educación Primaria. Este recurso integra el estudio de los ecosistemas con el desarrollo de la competencia digital a través de la curación de contenidos y la creación de un producto final multimedia.&lt;/p&gt;
&lt;p&gt;&lt;strong&gt;Licencia de uso: &lt;/strong&gt;Este recurso se publica bajo una licencia Creative Commons Atribución-CompartirIgual (BY-SA). Esto permite a otros docentes utilizar, adaptar y compartir el material siempre que se reconozca la autoría y se mantenga la misma licencia en las obras derivadas.&lt;br&gt;&lt;/p&gt;&lt;p class="clearfix"&gt;&lt;/p&gt;&lt;/div&gt;
            &lt;/div&gt;&lt;/div&gt;&lt;/div&gt;</htmlView><jsonProperties>{"ideviceId":"20260415194001424SCS","textInfoDurationInput":"","textInfoDurationTextInput":"Duración","textInfoParticipantsInput":"","textInfoParticipantsTextInput":"Agrupamiento","textTextarea":"&lt;p&gt;&lt;strong&gt;Autoría: &lt;/strong&gt;Alba Isabel Núñez Guzmán. &lt;/p&gt;\n&lt;p&gt;&lt;strong&gt;Descripción del recurso:&lt;/strong&gt; Situación de Aprendizaje (SdA) titulada \"Guardianes de la Biodiversidad\", diseñada para alumnos de 5.º de Educación Primaria. Este recurso integra el estudio de los ecosistemas con el desarrollo de la competencia digital a través de la curación de contenidos y la creación de un producto final multimedia.&lt;/p&gt;\n&lt;p&gt;&lt;strong&gt;Licencia de uso: &lt;/strong&gt;Este recurso se publica bajo una licencia Creative Commons Atribución-CompartirIgual (BY-SA). Esto permite a otros docentes utilizar, adaptar y compartir el material siempre que se reconozca la autoría y se mantenga la misma licencia en las obras derivadas.&lt;br /&gt;&lt;/p&gt;","textFeedbackInput":"Mostrar retroalimentación","textFeedbackTextarea":""}</jsonProperties><odeComponentsOrder>1</odeComponentsOrder><odeComponentsProperties><odeComponentsProperty><key>visibility</key><value>true</value></odeComponentsProperty><odeComponentsProperty><key>teacherOnly</key><value>false</value></odeComponentsProperty><odeComponentsProperty><key>identifier</key><value/></odeComponentsProperty><odeComponentsProperty><key>cssClass</key><value/></odeComponentsProperty></odeComponentsProperties></odeComponent></odeComponents></odePagStructure></odePagStructures></odeNavStructure></odeNavStructures></ode>
